blackduck_kb/Authentication.py
blackduck_kb/KBClient.py
blackduck_kb/Utils.py
blackduck_kb/__init__.py
blackduck_kb/__version__.py
blackduck_kb-0.0.1.dist-info/METADATA
blackduck_kb-0.0.1.dist-info/WHEEL
blackduck_kb-0.0.1.dist-info/top_level.txt
blackduck_kb-0.0.1.dist-info/RECORD
