Metadata-Version: 2.1
Name: blackduck-kb
Version: 0.0.1
Summary: Package for using the Synopsys Black Duck KB REST API.
Home-page: https://sig-gitlab.internal.synopsys.com/gsnyder/blackduck_kb
Author: Glenn Snyder
Author-email: gsnyder@synopsys.com
License: Apache
Keywords: api
Platform: UNKNOWN
Classifier: License :: OSI Approved :: Apache Software License
Classifier: Programming Language :: Python
Classifier: Programming Language :: Python :: 3
Classifier: Programming Language :: Python :: 3.6
Classifier: Programming Language :: Python :: Implementation :: CPython
Classifier: Programming Language :: Python :: Implementation :: PyPy
Requires-Python: >=3.6.0
Requires-Dist: requests
